<annotation>
  <folder>train</folder>
  <filename>sim_0312</filename>
  <path>/home/ernesto/udacity/models/object_detection/tl_classifier/data_sim/images/train/sim_0312.jpg</path>
  <source>
    <database>Unknown</database>
  </source>
  <size>
    <width>800</width>
    <height>600</height>
    <depth>3</depth>
  </size>
  <segmented>0</segmented>
  <object>
    <name>red</name>
    <pose>Unspecified</pose>
    <truncated>0</truncated>
    <difficult>0</difficult>
    <bndbox>
      <xmin>655</xmin>
      <ymin>453</ymin>
      <xmax>684</xmax>
      <ymax>513</ymax>
    </bndbox>
  </object>
  <object>
    <name>red</name>
    <pose>Unspecified</pose>
    <truncated>0</truncated>
    <difficult>0</difficult>
    <bndbox>
      <xmin>540</xmin>
      <ymin>452</ymin>
      <xmax>570</xmax>
      <ymax>513</ymax>
    </bndbox>
  </object>
  <object>
    <name>red</name>
    <pose>Unspecified</pose>
    <truncated>0</truncated>
    <difficult>0</difficult>
    <bndbox>
      <xmin>429</xmin>
      <ymin>451</ymin>
      <xmax>457</xmax>
      <ymax>510</ymax>
    </bndbox>
  </object>
</annotation>
